globalmoo/__init__.py
globalmoo/client.py
globalmoo/credentials.py
globalmoo/enums/__init__.py
globalmoo/enums/event_name.py
globalmoo/enums/input_type.py
globalmoo/enums/objective_type.py
globalmoo/enums/stop_reason.py
globalmoo/exceptions/__init__.py
globalmoo/exceptions/base.py
globalmoo/exceptions/invalid_argument.py
globalmoo/exceptions/invalid_request.py
globalmoo/exceptions/invalid_response.py
globalmoo/exceptions/network_connection.py
globalmoo/models/__init__.py
globalmoo/models/account.py
globalmoo/models/base.py
globalmoo/models/error.py
globalmoo/models/event.py
globalmoo/models/inverse.py
globalmoo/models/model.py
globalmoo/models/objective.py
globalmoo/models/project.py
globalmoo/models/result.py
globalmoo/models/trial.py
globalmoo/request/__init__.py
globalmoo/request/base.py
globalmoo/request/create_model.py
globalmoo/request/create_project.py
globalmoo/request/initialize_inverse.py
globalmoo/request/load_developed_outputs.py
globalmoo/request/load_inversed_output.py
globalmoo/request/load_objectives.py
globalmoo/request/load_output_cases.py
globalmoo/request/read_models.py
globalmoo/request/read_trial.py
globalmoo/request/register_account.py
globalmoo/request/suggest_inverse.py
globalmoo/utils/__init__.py
globalmoo/utils/console.py
globalmoo_sdk-1.0.1.dist-info/METADATA
globalmoo_sdk-1.0.1.dist-info/WHEEL
globalmoo_sdk-1.0.1.dist-info/licenses/LICENSE
globalmoo_sdk-1.0.1.dist-info/RECORD
