Metadata-Version: 2.4
Name: globalmoo-sdk
Version: 1.0.1
Summary: globalMOO SDK for Python
Project-URL: Homepage, https://github.com/globalMOO/gmoo-sdk-python
Author-email: Matt Freeman <support@globalmoo.com>
License-File: LICENSE
Classifier: License :: OSI Approved :: MIT License
Classifier: Operating System :: OS Independent
Classifier: Programming Language :: Python :: 3
Requires-Python: >=3.10
Requires-Dist: httpx>=0.26.0
Requires-Dist: numpy==1.26.4
Requires-Dist: pydantic>=2.5.0
Requires-Dist: pytest-dotenv>=0.5.2
Requires-Dist: python-dotenv>=1.0.0
Requires-Dist: rich==13.9.4
Requires-Dist: tenacity>=8.2.3
